twistream/__init__.py
twistream/backends/__init__.py
twistream/backends/base.py
twistream/backends/mongodb.py
twistream/backends/sqlite.py
twistream/cli/__init__.py
twistream/cli/cli.py
twistream/log/__init__.py
twistream/log/log.py
twistream/twitter/__init__.py
twistream/twitter/client.py
twistream/twitter/listeners.py
twistream/twitter/models.py
twistream-0.1.4.dist-info/LICENSE.txt
twistream-0.1.4.dist-info/METADATA
twistream-0.1.4.dist-info/WHEEL
twistream-0.1.4.dist-info/entry_points.txt
twistream-0.1.4.dist-info/top_level.txt
twistream-0.1.4.dist-info/zip-safe
twistream-0.1.4.dist-info/RECORD
