Metadata-Version: 2.1
Name: twistream
Version: 0.1.4
Summary: Automate Twitter Stream data collection
Home-page: https://github.com/guillermo-carrasco/twistream
Author: Guillermo Carrasco
Author-email: guille.ch.88@gmail.com
License: UNKNOWN
Keywords: Social Media,Twitter,Data Mining,Data Collection
Platform: UNKNOWN
Classifier: Programming Language :: Python
Classifier: Programming Language :: Python :: 3
Requires-Dist: black
Requires-Dist: click
Requires-Dist: mypy
Requires-Dist: pymongo
Requires-Dist: pytest
Requires-Dist: pyyaml
Requires-Dist: sqlalchemy
Requires-Dist: sqlalchemy-stubs
Requires-Dist: tweepy
